licensr/__init__.py
licensr/licensr.py
licensr-0.1.1.dist-info/METADATA
licensr-0.1.1.dist-info/WHEEL
licensr-0.1.1.dist-info/entry_points.txt
licensr-0.1.1.dist-info/top_level.txt
licensr-0.1.1.dist-info/RECORD
