Metadata-Version: 2.1
Name: licensr
Version: 0.1.1
Summary: A CLI for licensing your project
Home-page: https://github.com/max-elia/licensr
Author: Max Elia Schweigkofler
Author-email: schweigkofler.max@gmail.com
License: UNKNOWN
Keywords: licenser licensing reuse open source
Platform: UNKNOWN
Classifier: Programming Language :: Python :: 3
Classifier: License :: OSI Approved :: MIT License
Classifier: Operating System :: OS Independent
